{
    "student_id": "202301_7",
    "student_name": "学生_7",
    "course_name": "算法设计与分析",
    "chapter_id": "ch04",
    "task_id": "task001",
    "dialogues": [
        {
            "round": 1,
            "student_input": "整理第5-6讲《动态规划》的知识体系，要求包含：动态规划的基本思想、与分治法的异同、四个基本要素（最优子结构、子问题重叠、状态转移方程、备忘录）、四个求解步骤、典型应用案例（钢条切割、矩阵连乘、最长公共子序列、0-1背包问题）。输出形式可以是思维导图、知识图谱或结构化大纲。",
            "model_output": "# 动态规划（第5-6讲）知识体系 — 结构化大纲\n## 一、动态规划基本思想\n- 核心：**将复杂问题分解为若干重叠子问题**，通过**记录子问题解**避免重复计算，自底向上/自顶向下求解原问题。\n- 本质：**空间换时间**，用存储换取指数级时间复杂度降低。\n## 二、动态规划与分治法异同\n### 相同点\n- 都采用**分治思想**：分解问题 → 求解子问题 → 合并解。\n### 不同点\n| 对比维度 | 分治法 | 动态规划 |\n| :--- | :--- | :--- |\n| 子问题关系 | **相互独立、无重叠** | **子问题大量重叠** |\n| 求解方式 | 自顶向下递归 | 自顶向下（备忘录）/自底向上迭代 |\n| 重复计算 | 无 | 有，需记录避免 |\n| 适用场景 | 子问题独立 | 最优子结构+子问题重叠 |\n## 三、动态规划四个基本要素\n1. **最优子结构**\n   - 问题最优解包含**子问题的最优解**，可由子问题最优推导出原问题最优。\n2. **子问题重叠**\n   - 递归求解时**多次重复计算相同子问题**，是DP高效的前提。\n3. **状态转移方程**\n   - 描述**当前状态如何由之前状态推导**，是DP核心公式。\n4. **备忘录（记忆化）**\n   - 用数组/表存储已求解子问题结果：\n     - 自顶向下：递归+备忘录\n     - 自底向上：迭代填表\n## 四、动态规划四个求解步骤\n1. **划分阶段**：按问题特征拆分为有序阶段。\n2. **定义状态**：用`dp[i][j]`等表示子问题解。\n3. **确定状态转移方程**：写出`dp[i]`与前驱状态关系。\n4. **确定边界与计算顺序**：给出初始条件，按顺序递推。\n## 五、典型应用案例（核心公式+思路）\n### 1. 钢条切割\n- 问题：长度n钢条，不同长度售价不同，求最大收益。\n- 状态：`dp[i]`=长度i钢条最大收益。\n- 转移：\n  \\[\n  dp[i] = \\max_{1\\leq k\\leq i}(price[k] + dp[i-k])\n  \\]\n- 边界：`dp[0]=0`。\n### 2. 矩阵连乘\n- 问题：求矩阵链相乘**最少乘法次数**。\n- 状态：`dp[i][j]`=矩阵`A_i~A_j`连乘最小代价。\n- 转移：\n  \\[\n  dp[i][j] =\n  \\begin{cases}\n  0 & i=j \\\\\n  \\min_{i\\leq k<j}(dp[i][k]+dp[k+1][j]+p_{i-1}p_k p_j) & i<j\n  \\end{cases}\n  \\]\n- 顺序：**按区间长度从小到大**计算。\n### 3. 最长公共子序列 LCS\n- 问题：求两序列最长公共子序列长度。\n- 状态：`dp[i][j]`=序列1前i个、序列2前j个的LCS长度。\n- 转移：\n  \\[\n  dp[i][j] =\n  \\begin{cases}\n  dp[i-1][j-1]+1 & s1[i]=s2[j] \\\\\n  \\max(dp[i-1][j],dp[i][j-1]) & s1[i]\\neq s2[j]\n  \\end{cases}\n  \\]\n- 边界：`dp[0][j]=dp[i][0]=0`。\n### 4. 0-1 背包问题\n- 问题：n物品、背包容量C，每件只能选/不选，价值最大。\n- 状态：`dp[i][j]`=前i件物品、容量j时最大价值。\n- 转移：\n  \\[\n  dp[i][j] =\n  \\begin{cases}\n  dp[i-1][j] & w[i]>j \\\\\n  \\max(dp[i-1][j], dp[i-1][j-w[i]]+v[i]) & w[i]\\leq j\n  \\end{cases}\n  \\]\n- 可优化为**一维DP**：`dp[j] = max(dp[j], dp[j-w[i]]+v[i])`，**逆序遍历**。\n---\n如果你需要，我可以把这份大纲**转成可直接复制到PPT的思维导图格式**，或生成**Markdown思维导图/XMind文本结构**。"
        },
        {
            "round": 2,
            "student_input": "动态规划的状态转移方程怎么推导？",
            "model_output": "我给你一套**通用、可直接套用**的「状态转移方程推导套路」，一步一步跟着走，几乎所有DP题都能推出来。不讲虚的，全是做题能用的步骤。\n---\n# 一、推导状态转移方程的 **4 步万能法**\n## 第1步：先定义状态（最关键）\n问自己：\n**我要用 dp[?] 表示什么？**\n常见写法：\n- 一维：`dp[i]` = 前 i 个物品 / 长度为 i 的最优解\n- 二维：`dp[i][j]` = 前 i 个物品，背包容量 j 时的最优解\n**状态必须满足：能通过更小的子问题推出来。**\n---\n## 第2步：找「最后一步决策」\n对当前状态 `dp[i]` 或 `dp[i][j]`，**最后一步能做什么选择？**\n例子：\n- 钢条切割：最后切一段 k\n- 0-1背包：选 or 不选第 i 个物品\n- LCS：当前字符相等 or 不等\n- 矩阵连乘：最后一次乘的位置 k\n**决策 = 转移的分支**\n---\n## 第3步：把决策翻译成公式\n把“最后一步怎么做”写成 **dp[i] = 由前面哪些dp算出来**。\n通用句式：\n> dp[i] = max / min ( 子问题1 , 子问题2 , ... )\n---\n## 第4步：补边界条件\n- `dp[0]`\n- `dp[i][0]`\n- `dp[0][j]`\n保证递推能开始、不会越界。\n---\n# 二、用 4 步法 **现场推一遍**（带你真正学会）\n我用最经典的4个题演示，你看完就会自己推。\n---\n## 1）钢条切割\n### ① 定义状态\n`dp[i]` = 长度为 i 的钢条最大收益\n### ② 最后一步决策\n最后切下一段长度 k，剩下 i−k 继续最优切割。\n### ③ 写转移\ndp[i] = max( price[k] + dp[i−k] )，k=1~i\n### ④ 边界\ndp[0] = 0\n---\n## 2）0-1 背包\n### ① 定义状态\n`dp[i][j]` = 前 i 个物品，背包容量 j 的最大价值\n### ② 最后一步决策\n对第 i 个物品：\n- 不选：继承 `dp[i-1][j]`\n- 选：`dp[i-1][j-w[i]] + v[i]`\n### ③ 转移\n```\ndp[i][j] = max(\n   dp[i-1][j],            // 不选\n   dp[i-1][j-w[i]] + v[i] // 选\n)\n```\n### ④ 边界\ndp[0][j] = 0\ndp[i][0] = 0\n---\n## 3）最长公共子序列 LCS\n### ① 状态\n`dp[i][j]` = s1前i个、s2前j个的LCS长度\n### ② 最后一步\n- s1[i] == s2[j]：各退一步 +1\n- 不等：取左边/上边最大\n### ③ 转移\n```\nif s1[i] == s2[j]:\n   dp[i][j] = dp[i-1][j-1] + 1\nelse:\n   dp[i][j] = max(dp[i-1][j], dp[i][j-1])\n```\n### ④ 边界\ndp[0][j] = 0\ndp[i][0] = 0\n---\n## 4）矩阵连乘\n### ① 状态\n`dp[i][j]` = 矩阵 i~j 连乘最小代价\n### ② 最后一步\n在 k 处分开：左边 i~k，右边 k+1~j\n### ③ 转移\n```\ndp[i][j] = min{ dp[i][k] + dp[k+1][j] + p[i-1]p[k]p[j] }, i ≤ k < j\n```\n### ④ 边界\ndp[i][i] = 0\n---\n# 三、你自己推转移方程的 **万能口诀**\n1. **先定 dp 表示什么**（状态）\n2. **看最后一步能干嘛**（决策）\n3. **把决策写成 max/min**（转移）\n4. **补 dp[0] 或 dp[i][0]**（边界）\n一句话：\n**状态 → 最后一步 → 公式 → 边界**\n---\n# 四、我可以带你**现场练手**\n你随便说一道DP题，我可以带你：\n- 一步步推状态\n- 一步步推转移方程\n- 写出可直接用的代码\n你要练哪道？\n（比如：爬楼梯、零钱兑换、最长上升子序列、完全背包…）"
        },
        {
            "round": 3,
            "student_input": "钢条切割问题中 其状态转移方程是怎样的 请给我详细的推导过程 并结合实例",
            "model_output": "# 钢条切割问题：状态转移方程详细推导（附实例）\n钢条切割是动态规划最入门的经典案例，我会从**问题定义→状态定义→决策分析→方程推导→实例计算** 一步步拆解，确保你能完全理解每一步的逻辑。\n## 一、先明确钢条切割问题\n### 问题描述\n给定一根长度为 `n` 的钢条，以及一个价格表 `price[1...n]`（`price[k]` 表示长度为 `k` 的钢条的售价）。\n要求：将钢条切割成若干段（也可以不切割），使得总收益最大。\n### 示例价格表（后续实例用）\n| 长度k | 1 | 2 | 3 | 4 | 5  | 6  | 7  | 8  | 9  | 10 |\n|-------|---|---|---|---|----|----|----|----|----|----|\n| 价格p | 1 | 5 | 8 | 9 | 10 | 17 | 17 | 20 | 24 | 30 |\n比如：长度为4的钢条，切割方式有：\n- 不切：收益9；\n- 切1+3：收益1+8=9；\n- 切2+2：收益5+5=10（最优）；\n- 切1+1+2：收益1+1+5=7；\n- 切1+1+1+1：收益4。\n## 二、状态转移方程推导（核心步骤）\n### 步骤1：定义状态（明确dp[i]的含义）\n动态规划的核心是“定义状态”，状态要能覆盖子问题且可递推。\n**定义**：`dp[i]` 表示长度为 `i` 的钢条切割后能获得的**最大收益**。\n### 步骤2：分析“最后一步决策”（找到子问题关联）\n对于长度为 `i` 的钢条，我们考虑**第一次切割**（或最后一段）的长度：\n- 假设我们切下第一段长度为 `k`（`k` 的取值范围：1 ≤ k ≤ i）；\n- 剩下的钢条长度为 `i - k`，其最大收益是 `dp[i - k]`；\n- 此时总收益 = 长度k的售价 `price[k]` + 剩余长度的最大收益 `dp[i - k]`。\n### 步骤3：推导状态转移方程（取所有决策的最大值）\n要得到 `dp[i]`，需要遍历所有可能的切割长度 `k`，取总收益的最大值：\n\\[\ndp[i] = \\max_{1 \\leq k \\leq i} \\left( price[k] + dp[i - k] \\right)\n\\]\n**补充边界条件**：当钢条长度为0时（`i=0`），没有收益，因此 `dp[0] = 0`。\n### 步骤4：验证逻辑（为什么这样推导是对的？）\n- 覆盖所有切割方式：`k` 遍历1~i，相当于枚举了“切1段、切2段…切i段”的所有可能；\n- 最优子结构：`dp[i]` 的最优解依赖于 `dp[i-k]` 的最优解，符合动态规划的核心思想；\n- 避免重复计算：通过存储 `dp[i]`，后续计算更长钢条时可直接复用，而非重复递归。\n## 三、结合实例完整计算（以n=4为例）\n用前面的价格表，一步步计算 `dp[1]` 到 `dp[4]`，验证方程的正确性。\n### 已知条件\n- `price[1]=1, price[2]=5, price[3]=8, price[4]=9`\n- 边界：`dp[0] = 0`\n### 计算dp[1]（长度1的钢条）\n`k` 只能取1：\n\\[\ndp[1] = price[1] + dp[0] = 1 + 0 = 1\n\\]\n→ 长度1的钢条不切割，最大收益1。\n### 计算dp[2]（长度2的钢条）\n`k` 可取1或2：\n- k=1：`price[1] + dp[1] = 1 + 1 = 2`；\n- k=2：`price[2] + dp[0] = 5 + 0 = 5`；\n取最大值：`dp[2] = max(2,5) = 5`。\n→ 长度2的钢条不切割，最大收益5。\n### 计算dp[3]（长度3的钢条）\n`k` 可取1、2、3：\n- k=1：`price[1] + dp[2] = 1 + 5 = 6`；\n- k=2：`price[2] + dp[1] = 5 + 1 = 6`；\n- k=3：`price[3] + dp[0] = 8 + 0 = 8`；\n取最大值：`dp[3] = max(6,6,8) = 8`。\n→ 长度3的钢条不切割，最大收益8。\n### 计算dp[4]（长度4的钢条）\n`k` 可取1、2、3、4：\n- k=1：`price[1] + dp[3] = 1 + 8 = 9`；\n- k=2：`price[2] + dp[2] = 5 + 5 = 10`；\n- k=3：`price[3] + dp[1] = 8 + 1 = 9`；\n- k=4：`price[4] + dp[0] = 9 + 0 = 9`；\n取最大值：`dp[4] = max(9,10,9,9) = 10`。\n→ 长度4的钢条切成2+2，最大收益10（和之前分析一致）。\n## 四、完整代码实现（验证推导）\n下面是自底向上的动态规划代码，输入价格表和钢条长度，输出最大收益：\n```python\ndef cut_rod(price, n):\n    # 初始化dp数组，dp[0]=0，dp[1...n]初始为0\n    dp = [0] * (n + 1)\n    \n    # 自底向上计算dp[1]到dp[n]\n    for i in range(1, n + 1):\n        max_profit = 0  # 记录当前长度i的最大收益\n        # 遍历所有可能的切割长度k\n        for k in range(1, i + 1):\n            # 计算当前切割方式的收益：price[k-1]是因为列表索引从0开始\n            current_profit = price[k-1] + dp[i - k]\n            # 更新最大收益\n            if current_profit > max_profit:\n                max_profit = current_profit\n        dp[i] = max_profit\n    \n    return dp[n]\n# 测试实例：价格表对应长度1-10，计算长度4的最大收益\nprice = [1, 5, 8, 9, 10, 17, 17, 20, 24, 30]\nn = 4\nprint(f\"长度为{n}的钢条最大收益：{cut_rod(price, n)}\")  # 输出10\n```\n### 代码说明\n- `price[k-1]`：因为Python列表索引从0开始，`price[0]` 对应长度1的价格，`price[1]` 对应长度2的价格，以此类推；\n- 外层循环 `i` 遍历钢条长度（1~n），内层循环 `k` 遍历所有可能的切割长度；\n- 每一步都用 `max_profit` 记录当前长度的最大收益，最终存入 `dp[i]`。\n## 五、扩展：计算n=10的结果（验证方程通用性）\n用同样的方程计算长度10的钢条：\n- `dp[10] = max(price[k] + dp[10-k])`（k=1~10）；\n- 最终计算得 `dp[10] = 30`（不切割，直接卖长度10的钢条收益最大）。\n---\n### 总结\n1. 钢条切割的状态转移方程核心是**枚举所有切割点k**，取 `price[k] + dp[i-k]` 的最大值，本质是“分解子问题+最优子结构”；\n2. 状态 `dp[i]` 定义为“长度i的最大收益”是关键，边界条件 `dp[0]=0` 保证了递推的起点；\n3. 推导的核心逻辑：**先定状态→分析最后一步决策→枚举所有决策取最值→补充边界**，这套逻辑可迁移到所有动态规划问题。"
        },
        {
            "round": 4,
            "student_input": "试分析该过程中的时间复杂度与空间复杂度 并对比暴力递归法与动态规划法在这两个指标上有何不同",
            "model_output": "# 钢条切割问题：时间/空间复杂度分析（暴力递归 vs 动态规划）\n我会先拆解**动态规划法**的时间/空间复杂度，再分析**暴力递归法**的复杂度，最后通过对比表清晰展示两者差异，帮你理解“空间换时间”的本质。\n## 一、动态规划法（自底向上）的复杂度分析\n先回顾动态规划解法的核心逻辑：\n```python\n# 核心双层循环\nfor i in range(1, n+1):          # 外层：计算长度1~n的钢条\n    for k in range(1, i+1):      # 内层：枚举长度i的所有切割点k\n        current_profit = price[k-1] + dp[i-k]\n```\n### 1. 时间复杂度\n- 外层循环执行 `n` 次（`i=1` 到 `i=n`）；\n- 内层循环：\n  - 当 `i=1` 时，内层执行1次；\n  - 当 `i=2` 时，内层执行2次；\n  - ...\n  - 当 `i=n` 时，内层执行n次；\n- 总执行次数 = \\(1 + 2 + 3 + ... + n = \\frac{n(n+1)}{2}\\)；\n- 忽略常数项和低次项，时间复杂度为 **\\(O(n^2)\\)**。\n### 2. 空间复杂度\n- 动态规划解法仅额外使用了一个长度为 `n+1` 的 `dp` 数组（存储子问题解）；\n- 没有其他额外的大规模空间消耗；\n- 空间复杂度为 **\\(O(n)\\)**（若优化为仅存储必要状态，可压缩到 \\(O(1)\\)，但基础版本为 \\(O(n)\\)）。\n## 二、暴力递归法的复杂度分析\n暴力递归的核心思路：直接枚举所有切割方式，递归计算每一种切割的收益，取最大值。"
        }
    ],
    "final_report": "",
    "reflection": ""
}