{
  "student_id": "2026002",
  "student_name": "李四",
  "course_name": "计算机网络",
  "chapter_id": "ch04",
  "task_id": "task003",
  "dialogues": [
    {"round": 1, "student_input": "ARP协议是什么？", "model_output": "ARP用于IP转MAC。"},
    {"round": 2, "student_input": "工作原理是什么？", "model_output": "广播请求，单播响应。"},
    {"round": 3, "student_input": "有安全风险吗？", "model_output": "有ARP欺骗。"},
    {"round": 4, "student_input": "怎么防御？", "model_output": "使用防火墙或动态检测。"},
    {"round": 5, "student_input": "还有吗？", "model_output": "还有静态绑定。"},
    {"round": 6, "student_input": "明白了，谢谢。", "model_output": "不客气。"},
    {"round": 7, "student_input": "能总结下吗？", "model_output": "ARP协议是网络层与链路层的桥梁，存在安全隐患。"},
    {"round": 8, "student_input": "好的。", "model_output": "还有其他问题吗？"},
    {"round": 9, "student_input": "没有了。", "model_output": "好的，任务完成。"},
    {"round": 10, "student_input": "完成。", "model_output": "好的，已记录。"}
  ],
  "final_report": "ARP是IP转MAC的协议，有欺骗风险，可以用DAI防御。",
  "reflection": "学会了ARP的基本概念。"
}